statesman.py
statesman-1.0.5.dist-info/LICENSE
statesman-1.0.5.dist-info/METADATA
statesman-1.0.5.dist-info/WHEEL
statesman-1.0.5.dist-info/RECORD
