Metadata-Version: 2.1
Name: statesman
Version: 1.0.5
Summary: A modern state machine library.
Home-page: https://github.com/opsani/statesman
License: Apache-2.0
Author: Blake Watters
Author-email: blake@opsani.com
Requires-Python: >=3.8,<3.13
Classifier: License :: OSI Approved :: Apache Software License
Classifier: Programming Language :: Python :: 3
Classifier: Programming Language :: Python :: 3.8
Classifier: Programming Language :: Python :: 3.9
Classifier: Programming Language :: Python :: 3.10
Classifier: Programming Language :: Python :: 3.11
Classifier: Programming Language :: Python :: 3.12
Requires-Dist: pydantic (>=2.4,<3.0)
Project-URL: Repository, https://github.com/opsani/statesman
